lab2/case_alu.v
module eight_bit_alu_case(input [7:0] a, b, input [2:0] sel, output reg [7:0] o, output reg c);

always @(*)
begin
c = 1'b0;
case (sel)
3'b000: {c,o} = a+b;
3'b001: {c,o} = a-b;
3'b010: o = a&b;
3'b011: o = a|b;
3'b100: o = a^b;
3'b101: o = ~a;
3'b110: o = a<<1;
3'b111: o = a>>1;
default: ;
endcase
end

endmodule

lab2/case_alu_tb.v
`timescale 1ns / 1ps

module eight_bit_alu_case_tb;

reg [7:0] a, b;
reg [2:0] sel;
wire [7:0] o;
wire c;

eight_bit_alu_case alu(a, b, sel, o, c);

initial begin
$monitor("t=%0t sel=%b a=%b b=%b o=%b c=%b", $time, sel, a, b, o, c);

$dumpfile("eight_bit_alu.vcd");
$dumpvars(0,alu);

a=8'b00001111;
b=8'b00000001;

sel=3'b000;
#100;

sel=3'b001;
#100;

sel=3'b010;
#100;

sel=3'b011;
#100;

sel=3'b100;
#100;

sel=3'b101;
#100;

sel=3'b110;
#100;

sel=3'b111;
#100;

end
endmodule

lab2/eight_bit_alu.vcd
$date
	Thu Jun 25 15:12:41 2026
$end
$version
	Icarus Verilog
$end
$timescale
	1ps
$end
$scope module eight_bit_alu_case_tb $end
$scope module alu $end
$var wire 8 ! a [7:0] $end
$var wire 8 " b [7:0] $end
$var wire 3 # sel [2:0] $end
$var reg 1 $ c $end
$var reg 8 % o [7:0] $end
$upscope $end
$upscope $end
$enddefinitions $end
$comment Show the parameter values. $end
$dumpall
$end
#0
$dumpvars
b10000 %
0$
b0 #
b1 "
b1111 !
$end
#100000
b10 %
b1 !
#200000
b0 %
b1 #
#300000
b1 %
b10 #
#400000
b11 #
#500000
b0 %
b100 #
#600000
b11111110 %
b101 #
#700000
b10 %
b110 #
#800000
b0 %
b111 #
