lab2/case_alu.v
module eight_bit_alu_case(input [7:0] a, b, input [2:0] sel, output reg [7:0] o, output reg c);

always @(*)
begin
c = 1'b0;
case (sel)
3'b000:o=a;
3'b001: {c,o} = a+b;
3'b010: o = a&b;
3'b011: o = a|b;
default: ;
endcase
end

endmodule

lab2/two_compliment.v
module twos_compliment(input [7:0] inp, output [7:0] out);
assign out = ~inp + 1;
endmodule

lab2/reg_file.v
module reg_file(input clk, input [2:0] read_reg1, read_reg2, write_reg, input write_enable, input [7:0] data, output [7:0] reg_out1, reg_out2);
reg [7:0] regs [0:7];

assign reg_out1 = regs[read_reg1];
assign reg_out2 = regs[read_reg2];

always @(posedge clk)
    if (write_enable) regs[write_reg] <= data;
endmodule

lab2/control.v
module control(input [7:0] opcode, output reg [7:0] immediate, output reg [2:0] read_reg1,
output reg [2:0] read_reg2, output reg [2:0] write_reg, output reg write_enable, output reg comp, output reg imm_reg2, output reg [2:0] alu_sel);

always @(*)
begin
read_reg1 = 3'b000;
read_reg2 = 3'b000;
write_reg = 3'b000;
write_enable = 1'b1;
comp = 1'b0;
imm_reg2 = 1'b0;
immediate = 8'b0;
alu_sel = 3'b000;

case (opcode)
8'b00000000: begin read_reg1=3'd0; read_reg2=3'd1; write_reg=3'd0; end // ADD A,B
8'b00000001: begin read_reg1=3'd2; read_reg2=3'd3; write_reg=3'd2; end // ADD C,D
8'b00000010: begin read_reg1=3'd4; read_reg2=3'd5; write_reg=3'd4; end // ADD E,F
8'b00000011: begin read_reg1=3'd6; read_reg2=3'd7; write_reg=3'd6; end // ADD G,H
default: write_enable = 1'b0;
endcase

end
endmodule

lab2/top.v
module top(input clk, input [7:0] ins);

wire [7:0] immediate;
wire [2:0] read_reg1, read_reg2, write_reg, alu_sel;
wire write_enable, comp, imm_reg2;

control cu(ins, immediate, read_reg1, read_reg2, write_reg, write_enable, comp, imm_reg2, alu_sel);

wire [7:0] reg_out1, reg_out2;
wire [7:0] data;

reg_file rg(clk, read_reg1, read_reg2, write_reg, write_enable, data, reg_out1, reg_out2);

wire [7:0] reg_comp;
twos_compliment tc(reg_out2, reg_comp);

wire [7:0] im_reg;
assign im_reg = comp ? reg_comp : reg_out2;

wire [7:0] op1;
assign op1 = imm_reg2 ? immediate : im_reg;

wire [7:0] o;
wire c;
eight_bit_alu_case alu(op1, reg_out1, alu_sel, o, c);

assign data = o;

endmodule

lab2/top_tb.v
`timescale 1ns / 1ps

module top_tb;

reg clk;
reg [7:0] ins;

top uut(clk, ins);

always #5 clk = ~clk;

initial begin
$monitor("t=%0t ins=%b wr=%d we=%b data=%d", $time, ins, uut.write_reg, uut.write_enable, uut.data);

$dumpfile("top.vcd");
$dumpvars(0,uut);

clk=0;

uut.rg.regs[0]=8'd5;
uut.rg.regs[1]=8'd3;
uut.rg.regs[2]=8'd10;
uut.rg.regs[3]=8'd4;
uut.rg.regs[4]=8'd8;
uut.rg.regs[5]=8'd1;
uut.rg.regs[6]=8'd20;
uut.rg.regs[7]=8'd6;

ins=8'b00000000; // ADD A,B -> 8
#10;

ins=8'b00000001; // ADD C,D -> 14
#10;

ins=8'b00000010; // ADD E,F -> 9
#10;

ins=8'b00000011; // ADD G,H -> 26
#10;

$finish;
end
endmodule

lab2/top.vcd
$date
	Thu Jul  2 11:33:46 2026
$end
$version
	Icarus Verilog
$end
$timescale
	1ps
$end
$scope module top_tb $end
$scope module uut $end
$var wire 1 ! clk $end
$var wire 8 " data [7:0] $end
$var wire 8 # ins [7:0] $end
$var wire 3 $ write_reg [2:0] $end
$var wire 1 % write_enable $end
$var wire 8 & reg_out2 [7:0] $end
$var wire 8 ' reg_out1 [7:0] $end
$var wire 8 ( reg_comp [7:0] $end
$var wire 3 ) read_reg2 [2:0] $end
$var wire 3 * read_reg1 [2:0] $end
$var wire 8 + op1 [7:0] $end
$var wire 8 , o [7:0] $end
$var wire 8 - immediate [7:0] $end
$var wire 1 . imm_reg2 $end
$var wire 8 / im_reg [7:0] $end
$var wire 1 0 comp $end
$var wire 1 1 c $end
$var wire 3 2 alu_sel [2:0] $end
$scope module alu $end
$var wire 8 3 a [7:0] $end
$var wire 3 4 sel [2:0] $end
$var wire 8 5 b [7:0] $end
$var reg 1 1 c $end
$var reg 8 6 o [7:0] $end
$upscope $end
$scope module cu $end
$var wire 8 7 opcode [7:0] $end
$var reg 3 8 alu_sel [2:0] $end
$var reg 1 0 comp $end
$var reg 1 . imm_reg2 $end
$var reg 8 9 immediate [7:0] $end
$var reg 3 : read_reg1 [2:0] $end
$var reg 3 ; read_reg2 [2:0] $end
$var reg 1 % write_enable $end
$var reg 3 < write_reg [2:0] $end
$upscope $end
$scope module rg $end
$var wire 1 ! clk $end
$var wire 8 = data [7:0] $end
$var wire 3 > read_reg1 [2:0] $end
$var wire 3 ? read_reg2 [2:0] $end
$var wire 8 @ reg_out1 [7:0] $end
$var wire 8 A reg_out2 [7:0] $end
$var wire 1 % write_enable $end
$var wire 3 B write_reg [2:0] $end
$upscope $end
$scope module tc $end
$var wire 8 C inp [7:0] $end
$var wire 8 D out [7:0] $end
$upscope $end
$upscope $end
$upscope $end
$enddefinitions $end
$comment Show the parameter values. $end
$dumpall
$end
#0
$dumpvars
b11111101 D
b11 C
b0 B
b11 A
b101 @
b1 ?
b0 >
b1000 =
b0 <
b1 ;
b0 :
b0 9
b0 8
b0 7
b1000 6
b101 5
b0 4
b11 3
b0 2
01
00
b11 /
0.
b0 -
b1000 ,
b11 +
b0 *
b1 )
b11111101 (
b101 '
b11 &
1%
b0 $
b0 #
b1000 "
0!
$end
#5000
b1011 "
b1011 =
b1011 ,
b1011 6
b1000 '
b1000 5
b1000 @
1!
#10000
b100 +
b100 3
b1110 "
b1110 =
b1110 ,
b1110 6
b11111100 (
b11111100 D
b100 /
b1010 '
b1010 5
b1010 @
b100 &
b100 A
b100 C
b10 $
b10 <
b10 B
b10 *
b10 :
b10 >
b11 )
b11 ;
b11 ?
0!
b1 #
b1 7
#15000
b10010 "
b10010 =
b10010 ,
b10010 6
b1110 '
b1110 5
b1110 @
1!
#20000
b1 +
b1 3
b11111111 (
b11111111 D
b1 /
b1001 "
b1001 =
b1001 ,
b1001 6
b1 &
b1 A
b1 C
b1000 '
b1000 5
b1000 @
b100 $
b100 <
b100 B
b101 )
b101 ;
b101 ?
b100 *
b100 :
b100 >
0!
b10 #
b10 7
#25000
b1010 "
b1010 =
b1010 ,
b1010 6
b1001 '
b1001 5
b1001 @
1!
#30000
b110 +
b110 3
b11111010 (
b11111010 D
b110 /
b11010 "
b11010 =
b11010 ,
b11010 6
b110 &
b110 A
b110 C
b10100 '
b10100 5
b10100 @
b110 $
b110 <
b110 B
b111 )
b111 ;
b111 ?
b110 *
b110 :
b110 >
0!
b11 #
b11 7
#35000
b100000 "
b100000 =
b100000 ,
b100000 6
b11010 '
b11010 5
b11010 @
1!
